{"dataSerie": [{"name": "Adecuado", "data": [15.817857142857141, 39.166666666666664, 24.27311320754717], "type": "bar", "color": "#00CD00"}, {"name": "Elemental", "data": [36.400000000000006, 44.88095238095238, 41.10967741935484], "type": "bar", "color": "#FED976"}, {"name": "Insuficiente", "data": [48.04912280701755, 17.626315789473683, 35.34166666666667], "type": "bar", "color": "#FF0000"}], "graficoTipo": "Graph 05", "seriesGrafico": ["Adecuado", "Elemental", "Insuficiente"], "titulo_general": "Proporci\u00f3n de alumnos por Nivel de Aprendizaje en la prueba SIMCE de Matem\u00e1ticas de 4to B\u00e1sico seg\u00fan Dependencia de Establecimiento Educacional", "detalle": "Aprendizaje Matem\u00e1ticas 4to B\u00e1sico por Dependencia", "label": ["Municipal", "Particular Pagados", "Subvencionados"]}