{"dataSerie": [{"name": "Empresas", "data": [8739, 8737, 7770, 7706, 7687, 7699, 7814, 7527, 7983, 8490, 9873, 11616, 15688, 19069, 20918, 20967, 25022], "type": "bar", "color": "#4F2270"}], "graficoTipo": "Graph 09", "seriesGrafico": ["Empresas"], "titulo_general": "Evoluci\u00f3n del N\u00famero de Empresas en el Rubro: Otros Servicios", "detalle": "Evoluci\u00f3n del N\u00famero de Empresas en el R", "unidad": "Empresas", "color": "#4F2270", "area_tematica_completa": "Empresas", "tema": "Empresas Rubro", "fuente": "SII", "label": [2005, 2006, 2007, 2008, 2009, 2010, 2011, 2012, 2013, 2014, 2015, 2016, 2017, 2018, 2019, 2020, 2021]}