[{"\u00c1rea Tem\u00e1tica":"Educaci\u00f3n","Tema":"Aprendizaje Lectura","ID":"educaniveles00001"},{"\u00c1rea Tem\u00e1tica":"Educaci\u00f3n","Tema":"Aprendizaje Lectura","ID":"educaniveles00002"},{"\u00c1rea Tem\u00e1tica":"Educaci\u00f3n","Tema":"Aprendizaje Lectura","ID":"educaniveles00003"},{"\u00c1rea Tem\u00e1tica":"Educaci\u00f3n","Tema":"Aprendizaje Lectura","ID":"educaniveles00004"},{"\u00c1rea Tem\u00e1tica":"Educaci\u00f3n","Tema":"Aprendizaje Matem\u00e1ticas","ID":"educaniveles00005"},{"\u00c1rea Tem\u00e1tica":"Educaci\u00f3n","Tema":"Aprendizaje Matem\u00e1ticas","ID":"educaniveles00006"},{"\u00c1rea Tem\u00e1tica":"Educaci\u00f3n","Tema":"Aprendizaje Matem\u00e1ticas","ID":"educaniveles00007"},{"\u00c1rea Tem\u00e1tica":"Educaci\u00f3n","Tema":"Aprendizaje Matem\u00e1ticas","ID":"educaniveles00008"},{"\u00c1rea Tem\u00e1tica":"Educaci\u00f3n","Tema":"Aprendizaje Lectura","ID":"educaniveles00009"},{"\u00c1rea Tem\u00e1tica":"Educaci\u00f3n","Tema":"Aprendizaje Lectura","ID":"educaniveles00010"},{"\u00c1rea Tem\u00e1tica":"Educaci\u00f3n","Tema":"Aprendizaje Lectura","ID":"educaniveles00011"},{"\u00c1rea Tem\u00e1tica":"Educaci\u00f3n","Tema":"Aprendizaje Lectura","ID":"educaniveles00012"},{"\u00c1rea Tem\u00e1tica":"Educaci\u00f3n","Tema":"Aprendizaje Matem\u00e1ticas","ID":"educaniveles00013"},{"\u00c1rea Tem\u00e1tica":"Educaci\u00f3n","Tema":"Aprendizaje Matem\u00e1ticas","ID":"educaniveles00014"},{"\u00c1rea Tem\u00e1tica":"Educaci\u00f3n","Tema":"Aprendizaje Matem\u00e1ticas","ID":"educaniveles00015"},{"\u00c1rea Tem\u00e1tica":"Educaci\u00f3n","Tema":"Aprendizaje Matem\u00e1ticas","ID":"educaniveles00016"},{"\u00c1rea Tem\u00e1tica":"Educaci\u00f3n","Tema":"Aprendizaje Lectura","ID":"educaniveles00017"},{"\u00c1rea Tem\u00e1tica":"Educaci\u00f3n","Tema":"Aprendizaje Lectura","ID":"educaniveles00018"},{"\u00c1rea Tem\u00e1tica":"Educaci\u00f3n","Tema":"Aprendizaje Lectura","ID":"educaniveles00019"},{"\u00c1rea Tem\u00e1tica":"Educaci\u00f3n","Tema":"Aprendizaje Lectura","ID":"educaniveles00020"},{"\u00c1rea Tem\u00e1tica":"Educaci\u00f3n","Tema":"Aprendizaje Matem\u00e1ticas","ID":"educaniveles00021"},{"\u00c1rea Tem\u00e1tica":"Educaci\u00f3n","Tema":"Aprendizaje Matem\u00e1ticas","ID":"educaniveles00022"},{"\u00c1rea Tem\u00e1tica":"Educaci\u00f3n","Tema":"Aprendizaje Matem\u00e1ticas","ID":"educaniveles00023"},{"\u00c1rea Tem\u00e1tica":"Educaci\u00f3n","Tema":"Aprendizaje Matem\u00e1ticas","ID":"educaniveles00024"},{"\u00c1rea Tem\u00e1tica":"Educaci\u00f3n","Tema":"Aprendizaje Lectura","ID":"educaniveles00025"},{"\u00c1rea Tem\u00e1tica":"Educaci\u00f3n","Tema":"Aprendizaje Lectura","ID":"educaniveles00026"},{"\u00c1rea Tem\u00e1tica":"Educaci\u00f3n","Tema":"Aprendizaje Lectura","ID":"educaniveles00027"},{"\u00c1rea Tem\u00e1tica":"Educaci\u00f3n","Tema":"Aprendizaje Lectura","ID":"educaniveles00028"},{"\u00c1rea Tem\u00e1tica":"Educaci\u00f3n","Tema":"Aprendizaje Matem\u00e1ticas","ID":"educaniveles00029"},{"\u00c1rea Tem\u00e1tica":"Educaci\u00f3n","Tema":"Aprendizaje Matem\u00e1ticas","ID":"educaniveles00030"},{"\u00c1rea Tem\u00e1tica":"Educaci\u00f3n","Tema":"Aprendizaje Matem\u00e1ticas","ID":"educaniveles00031"},{"\u00c1rea Tem\u00e1tica":"Educaci\u00f3n","Tema":"Aprendizaje Matem\u00e1ticas","ID":"educaniveles00032"},{"\u00c1rea Tem\u00e1tica":"Educaci\u00f3n","Tema":"Aprendizaje Lectura","ID":"educaniveles00033"},{"\u00c1rea Tem\u00e1tica":"Educaci\u00f3n","Tema":"Aprendizaje Lectura","ID":"educaniveles00034"},{"\u00c1rea Tem\u00e1tica":"Educaci\u00f3n","Tema":"Aprendizaje Lectura","ID":"educaniveles00035"},{"\u00c1rea Tem\u00e1tica":"Educaci\u00f3n","Tema":"Aprendizaje Lectura","ID":"educaniveles00036"},{"\u00c1rea Tem\u00e1tica":"Educaci\u00f3n","Tema":"Aprendizaje Matem\u00e1ticas","ID":"educaniveles00037"},{"\u00c1rea Tem\u00e1tica":"Educaci\u00f3n","Tema":"Aprendizaje Matem\u00e1ticas","ID":"educaniveles00038"},{"\u00c1rea Tem\u00e1tica":"Educaci\u00f3n","Tema":"Aprendizaje Matem\u00e1ticas","ID":"educaniveles00039"},{"\u00c1rea Tem\u00e1tica":"Educaci\u00f3n","Tema":"Aprendizaje Matem\u00e1ticas","ID":"educaniveles00040"},{"\u00c1rea Tem\u00e1tica":"Educaci\u00f3n","Tema":"Aprendizaje Nivel Socioecon\u00f3mico","ID":"educaniveles00041"},{"\u00c1rea Tem\u00e1tica":"Educaci\u00f3n","Tema":"Aprendizaje Nivel Socioecon\u00f3mico","ID":"educaniveles00042"},{"\u00c1rea Tem\u00e1tica":"Educaci\u00f3n","Tema":"Aprendizaje Nivel Socioecon\u00f3mico","ID":"educaniveles00043"},{"\u00c1rea Tem\u00e1tica":"Educaci\u00f3n","Tema":"Aprendizaje Nivel Socioecon\u00f3mico","ID":"educaniveles00044"},{"\u00c1rea Tem\u00e1tica":"Educaci\u00f3n","Tema":"Aprendizaje Nivel Socioecon\u00f3mico","ID":"educaniveles00045"},{"\u00c1rea Tem\u00e1tica":"Educaci\u00f3n","Tema":"Aprendizaje Nivel Socioecon\u00f3mico","ID":"educaniveles00046"},{"\u00c1rea Tem\u00e1tica":"Educaci\u00f3n","Tema":"Aprendizaje Nivel Socioecon\u00f3mico","ID":"educaniveles00047"},{"\u00c1rea Tem\u00e1tica":"Educaci\u00f3n","Tema":"Aprendizaje Nivel Socioecon\u00f3mico","ID":"educaniveles00048"}]