{"data": [null, null, null, null, null, null, null, null, null, null, null, 3328.0, 2263.0, 2712.0, 2807.0, 4527.0, 4204.0, 4759.0, 8131.0, 6779.0, 6724.0, null, null, null], "titulo": "Bajo Riesgo Cardiovascular Mujeres", "titulo_largo": "Mujeres con Bajo Riesgo Cardiovascular en el PSCV", "tema": "Programa Cardiovascular", "tema_id": "programa_cardiovascular", "unidad": "personas", "ID2": "salud994", "Tipo": "PSCV", "Fuente": "Sin Fuente", "codcom": 13119, "area_tematica": "salud", "area_tematica_completa": "Salud"}