{"data": [null, null, null, null, null, null, null, null, null, 10597.7248692089, 11892.1540152296, 12177.8158859781, 8659.087393113, 10069.4940099177, 9072.3435265648, 9336.5727666551, 7701.4559307745, 10381.858580618, 14660.9398631918, 23063.0082874875, 13898.8297974406, null, null, null], "titulo": "Desempleados mujeres", "titulo_largo": "N\u00ba Desempleadas Mujeres Promedio Anual", "tema": "Desempleo", "tema_id": "desempleo", "unidad": "desempleadas", "ID2": "desempleo728", "Tipo": "Desempleo", "Fuente": "Min. Trabajo", "codcom": 13119, "area_tematica": "desempleo", "area_tematica_completa": "Desempleo"}