{"data": [null, null, null, null, 59.0, 37.0, 118.0, 218.0, 204.0, 241.0, 244.0, 311.0, 310.0, 269.0, 277.0, 294.0, 154.0, 156.0, 200.0, 171.0, 160.0, null, null, null], "titulo": "Denuncias GD: Robo Frustrado", "titulo_largo": "Frecuencia de Denuncias |Grupo Delictual: Robo frustrado", "tema": "Denuncias-Grupo Delictual", "tema_id": "denunciasgrupo_delictual", "unidad": "casos", "ID2": "delincuencia468", "Tipo": "Delincuencia", "Fuente": "CEAD", "codcom": 13119, "area_tematica": "delincuencia", "area_tematica_completa": "Delincuencia"}