{"data": [null, null, null, null, 6.0, 1.0, 6.0, 3.0, 7.0, 6.0, 6.0, 3.0, 3.0, 3.0, 4.0, 10.0, 18.0, 20.0, 42.0, 79.0, 98.0, null, null, null], "titulo": "Casos Policiales VIF no clasificado", "titulo_largo": "Frecuencia de Casos Policiales |Delito: Violencia intrafamiliar no clasificado", "tema": "Casos Policiales-VIF", "tema_id": "casos_policialesvif", "unidad": "casos", "ID2": "delincuencia512", "Tipo": "Delincuencia", "Fuente": "CEAD", "codcom": 13119, "area_tematica": "delincuencia", "area_tematica_completa": "Delincuencia"}